MillenniumUtils/__init__.py
millennium_core_utils-5.2.8.dist-info/METADATA
millennium_core_utils-5.2.8.dist-info/WHEEL
millennium_core_utils-5.2.8.dist-info/top_level.txt
millennium_core_utils-5.2.8.dist-info/RECORD
