Metadata-Version: 2.1
Name: millennium-core-utils
Version: 5.2.8
Summary: A support library for creating plugins with Millennium.
Home-page: https://github.com/SteamClientHomebrew/PluginComponents
Author: Steam Client Homebrew
Classifier: Intended Audience :: Developers
Classifier: License :: OSI Approved :: GNU Lesser General Public License v2 or later (LGPLv2+)
Classifier: Programming Language :: Python :: 3.11
Requires-Python: >=3.11.8
